fmutest/__init__.py
fmutest/instantiation.py
fmutest/optimization.py
fmutest/simulation.py
fmutest/fmi/__init__.py
fmutest/fmi/fmi2.py
fmutest/fmi/fmi2_inst.py
fmutest/tests/__init__.py
fmutest/tests/test_singlestep.py
fmutest/tests/utils.py
fmutest-0.0.6.dist-info/LICENSE
fmutest-0.0.6.dist-info/METADATA
fmutest-0.0.6.dist-info/WHEEL
fmutest-0.0.6.dist-info/top_level.txt
fmutest-0.0.6.dist-info/RECORD
