Metadata-Version: 2.1
Name: fmutest
Version: 0.0.6
Summary: Library for testing of energy FMUs, repository: https://lab.compute.dtu.dk/kofi/fmutest
Author: Konstantin Filonenko/DTU Compute
Author-email: kofi@dtu.dk
License: UNKNOWN
Platform: UNKNOWN
Classifier: Programming Language :: Python :: 3
Classifier: License :: OSI Approved :: BSD License
Classifier: Operating System :: OS Independent
Requires-Python: >=3.8
License-File: LICENSE
